pyometiff/__init__.py
pyometiff/omereader.py
pyometiff/omewriter.py
pyometiff/omexml.py
pyometiff-1.1.4.dist-info/LICENSE
pyometiff-1.1.4.dist-info/METADATA
pyometiff-1.1.4.dist-info/WHEEL
pyometiff-1.1.4.dist-info/RECORD
