Metadata-Version: 2.3
Name: pyometiff
Version: 1.1.4
Summary: Read and Write OME-TIFFs in Python
License: GPL-2.0-or-later
Author: Filippo Maria Castelli
Author-email: castelli@lens.unifi.it
Requires-Python: >=3.10
Classifier: License :: OSI Approved :: GNU General Public License v2 or later (GPLv2+)
Classifier: Programming Language :: Python :: 3
Classifier: Programming Language :: Python :: 3.10
Classifier: Programming Language :: Python :: 3.11
Classifier: Programming Language :: Python :: 3.12
Classifier: Programming Language :: Python :: 3.13
Requires-Dist: imagecodecs (>=2024.12.30)
Requires-Dist: lxml (>=5.3.2,<6.0.0)
Requires-Dist: numpy (>=1.26.4)
Requires-Dist: tifffile (>2020.10.1)
Project-URL: Homepage, https://github.com/filippocastelli/pyometiff
